docs/CHANGELOG.md
opsgenie_logger/__init__.py
opsgenie_logger/py.typed
opsgenie_logger-0.1.6.dist-info/LICENSE
opsgenie_logger-0.1.6.dist-info/WHEEL
opsgenie_logger-0.1.6.dist-info/METADATA
opsgenie_logger-0.1.6.dist-info/RECORD
