Metadata-Version: 2.1
Name: opsgenie-logger
Version: 0.1.6
Summary: Provides a logging handler for Atlassian OpsGenie
Home-page: https://github.com/triaxtec/opsgenie-logger
License: MIT
Keywords: opsgenie,logging
Author: Dylan Anthony
Author-email: danthony@triaxtec.com
Requires-Python: >=3.7.0,<4.0.0
Classifier: License :: OSI Approved :: MIT License
Classifier: Programming Language :: Python :: 3
Classifier: Programming Language :: Python :: 3.7
Requires-Dist: requests (>=2.22.0,<3.0.0)
Project-URL: Repository, https://github.com/triaxtec/opsgenie-logger
